doc/benchmarks.png
doc/impossible-triangle.jpeg
doc/inference-memory.png
doc/inference-throughput.png
doc/retention-dual-forms.jpeg
doc/retnet-scaling.jpeg
scripts/benchmark_inference.py
scripts/train_project_gutenberg.py
yet_another_retnet/__init__.py
yet_another_retnet/retention.py
yet_another_retnet/retnet.py
yet_another_retnet/utils/__init__.py
yet_another_retnet/utils/benchmark.py
yet_another_retnet/utils/gutenberg.py
yet_another_retnet/utils/profile.py
yet_another_retnet-0.5.1.dist-info/LICENSE
yet_another_retnet-0.5.1.dist-info/METADATA
yet_another_retnet-0.5.1.dist-info/WHEEL
yet_another_retnet-0.5.1.dist-info/top_level.txt
yet_another_retnet-0.5.1.dist-info/RECORD
