Metadata-Version: 2.1
Name: yet-another-retnet
Version: 0.5.1
Summary: yet-another-retnet
Author-email: Frank Odom <fodom@plainsight.ai>
License: MIT
Classifier: Programming Language :: Python :: 3
Requires-Python: >=3.8
License-File: LICENSE
Requires-Dist: einops
Requires-Dist: torch >=1.8
Provides-Extra: test
Requires-Dist: black ; extra == 'test'
Requires-Dist: kaleido ; extra == 'test'
Requires-Dist: mypy ; extra == 'test'
Requires-Dist: pre-commit ; extra == 'test'
Requires-Dist: plotly ; extra == 'test'
Requires-Dist: pytest ; extra == 'test'
Requires-Dist: pytest-cov ; extra == 'test'
Requires-Dist: ruff ; extra == 'test'
Requires-Dist: types-requests ; extra == 'test'
Provides-Extra: train
Requires-Dist: lightning ~=2.0.0 ; extra == 'train'
Requires-Dist: tensorboard ~=2.14.0 ; extra == 'train'
Requires-Dist: tiktoken ~=0.4.0 ; extra == 'train'
Requires-Dist: torchdata >=0.6.0 ; extra == 'train'
Requires-Dist: tqdm ; extra == 'train'
